templateapp/__init__.py
templateapp/__main__.py
templateapp/application.py
templateapp/config.py
templateapp/core.py
templateapp/exceptions.py
templateapp/main.py
templateapp-0.1.9.dist-info/LICENSE
templateapp-0.1.9.dist-info/METADATA
templateapp-0.1.9.dist-info/WHEEL
templateapp-0.1.9.dist-info/entry_points.txt
templateapp-0.1.9.dist-info/top_level.txt
templateapp-0.1.9.dist-info/RECORD
